LICENSE
MANIFEST.in
setup.cfg
setup.py
bin/configurator.py
yoconfigurator/__init__.py
yoconfigurator/base.py
yoconfigurator/credentials.py
yoconfigurator/dicts.py
yoconfigurator/filter.py
yoconfigurator/smush.py
yoconfigurator.egg-info/PKG-INFO
yoconfigurator.egg-info/SOURCES.txt
yoconfigurator.egg-info/dependency_links.txt
yoconfigurator.egg-info/top_level.txt
yoconfigurator/tests/__init__.py
yoconfigurator/tests/test_base.py
yoconfigurator/tests/test_configurator.py
yoconfigurator/tests/test_credentials.py
yoconfigurator/tests/test_dicts.py
yoconfigurator/tests/test_script.py
yoconfigurator/tests/test_smush.py